my_package/__init__.py
my_package/module1.py
my_package/module2.py
hello_world_package_Devendra-0.1.0.dist-info/METADATA
hello_world_package_Devendra-0.1.0.dist-info/WHEEL
hello_world_package_Devendra-0.1.0.dist-info/top_level.txt
hello_world_package_Devendra-0.1.0.dist-info/RECORD
